MANIFEST.in
README.rst
setup.py
collective/__init__.py
collective.opensearch.egg-info/PKG-INFO
collective.opensearch.egg-info/SOURCES.txt
collective.opensearch.egg-info/dependency_links.txt
collective.opensearch.egg-info/entry_points.txt
collective.opensearch.egg-info/namespace_packages.txt
collective.opensearch.egg-info/not-zip-safe
collective.opensearch.egg-info/requires.txt
collective.opensearch.egg-info/top_level.txt
collective/opensearch/README.txt
collective/opensearch/__init__.py
collective/opensearch/config.py
collective/opensearch/configure.zcml
collective/opensearch/setuphandlers.py
collective/opensearch/utils.py
collective/opensearch/vocabularies.py
collective/opensearch/browser/__init__.py
collective/opensearch/browser/atomview.pt
collective/opensearch/browser/atomview.py
collective/opensearch/browser/autodiscovery.pt
collective/opensearch/browser/baseview.py
collective/opensearch/browser/configure.zcml
collective/opensearch/browser/descriptionview.pt
collective/opensearch/browser/descriptionview.py
collective/opensearch/browser/htmlview.py
collective/opensearch/browser/jsonview.py
collective/opensearch/browser/opensearch.png
collective/opensearch/browser/osfolderview.pt
collective/opensearch/browser/osfolderview.py
collective/opensearch/browser/oslinkview.pt
collective/opensearch/browser/oslinkview.py
collective/opensearch/browser/osresults.pt
collective/opensearch/browser/rssview.pt
collective/opensearch/browser/rssview.py
collective/opensearch/browser/search.py
collective/opensearch/browser/settingsview.py
collective/opensearch/browser/suggestionview.py
collective/opensearch/browser/utils.py
collective/opensearch/browser/viewlets.py
collective/opensearch/content/__init__.py
collective/opensearch/content/configure.zcml
collective/opensearch/interfaces/__init__.py
collective/opensearch/interfaces/settings.py
collective/opensearch/portlets/__init__.py
collective/opensearch/portlets/configure.zcml
collective/opensearch/profiles/default/controlpanel.xml
collective/opensearch/profiles/default/factorytool.xml
collective/opensearch/profiles/default/metadata.xml
collective/opensearch/profiles/default/portlets.xml
collective/opensearch/profiles/default/registry.xml
collective/opensearch/profiles/default/types.xml
collective/opensearch/profiles/default/types/Folder.xml
collective/opensearch/profiles/default/types/Link.xml
