Metadata-Version: 1.1
Name: collective.opensearch
Version: 1.6
Summary: Collective Opensearch Collective.opensearch adds
Home-page: http://plone.org/products/plos
Author: Christian Ledermann
Author-email: christian.ledermann@gmail.com
License: GPL
Platform: UNKNOWN
Classifier: Framework :: Plone
Classifier: Intended Audience :: Developers
Classifier: Topic :: Internet :: WWW/HTTP :: Indexing/Search
Classifier: License :: OSI Approved :: GNU General Public License (GPL)
